[
  {
    "recipe_id": "MR_787_1",
    "title_original": "SAMBAL TERI GORENG",
    "title_normalized": "Sambal Teri Goreng",
    "region": "Rembang",
    "page_number": 787,
    "category": "Sambal",
    "ingredient_groups": [
      {
        "group_name": "utama",
        "original_header": "Bahan²",
        "ingredients": [
          {
            "original_text": "teri kering 1 ons.",
            "item_original": "teri kering",
            "item_normalized": "teri kering",
            "quantity": 1.0,
            "unit": "ons"
          },
          {
            "original_text": "kelapa ¼ btr.",
            "item_original": "kelapa",
            "item_normalized": "kelapa",
            "quantity": 0.25,
            "unit": "butir"
          },
          {
            "original_text": "minjak goreng 1 gls.",
            "item_original": "minjak goreng",
            "item_normalized": "minyak goreng",
            "quantity": 1.0,
            "unit": "gelas"
          }
        ]
      },
      {
        "group_name": "bumbu",
        "original_header": "Bumbu²",
        "ingredients": [
          {
            "original_text": "bawang putih 2 siung",
            "item_original": "bawang putih",
            "item_normalized": "bawang putih",
            "quantity": 2.0,
            "unit": "siung"
          },
          {
            "original_text": "lombok merah 5 bh.",
            "item_original": "lombok merah",
            "item_normalized": "cabai merah",
            "quantity": 5.0,
            "unit": "buah"
          },
          {
            "original_text": "lombok rawit 5 bh.",
            "item_original": "lombok rawit",
            "item_normalized": "cabai rawit",
            "quantity": 5.0,
            "unit": "buah"
          },
          {
            "original_text": "kemiri 4 bdj.",
            "item_original": "kemiri",
            "item_normalized": "kemiri",
            "quantity": 4.0,
            "unit": "biji"
          },
          {
            "original_text": "laos 1 pt.",
            "item_original": "laos",
            "item_normalized": "lengkuas",
            "quantity": 1.0,
            "unit": "potong"
          },
          {
            "original_text": "kentjur ½ rdj.",
            "item_original": "kentjur",
            "item_normalized": "kencur",
            "quantity": 0.5,
            "unit": "ruas jari"
          },
          {
            "original_text": "kuntji ½ rdj.",
            "item_original": "kuntji",
            "item_normalized": "kunci",
            "quantity": 0.5,
            "unit": "ruas jari"
          },
          {
            "original_text": "daun djeruk purut 2 lbr.",
            "item_original": "daun djeruk purut",
            "item_normalized": "daun jeruk purut",
            "quantity": 2.0,
            "unit": "lembar"
          },
          {
            "original_text": "asam 2 mata",
            "item_original": "asam",
            "item_normalized": "asam jawa",
            "quantity": 2.0,
            "unit": "mata"
          },
          {
            "original_text": "gula merah 1 sdt.",
            "item_original": "gula merah",
            "item_normalized": "gula merah",
            "quantity": 1.0,
            "unit": "sendok teh"
          },
          {
            "original_text": "terasi 1 sdt.",
            "item_original": "terasi",
            "item_normalized": "terasi",
            "quantity": 1.0,
            "unit": "sendok teh"
          }
        ]
      }
    ],
    "instructions": [
      "Teri dibersihkan, terus digoreng.",
      "Bumbu dihaluskan, kecuali lengkuas dan salam.",
      "Bumbu ditumis, dimasukkan teri, terakhir dimasukkan santan.",
      "Dimasak sampai kental."
    ]
  },
  {
    "recipe_id": "MR_787_2",
    "title_original": "SAMBAL TERONG",
    "title_normalized": "Sambal Terong",
    "region": null,
    "page_number": 787,
    "category": "Sambal",
    "ingredient_groups": [
      {
        "group_name": "utama",
        "original_header": "Bahan²",
        "ingredients": [
          {
            "original_text": "terong 2 bdj.",
            "item_original": "terong",
            "item_normalized": "terong",
            "quantity": 2.0,
            "unit": "biji"
          },
          {
            "original_text": "kelapa 1/3 btr.",
            "item_original": "kelapa",
            "item_normalized": "kelapa",
            "quantity": 0.33,
            "unit": "butir"
          }
        ]
      },
      {
        "group_name": "bumbu",
        "original_header": "Bumbu²",
        "ingredients": [
          {
            "original_text": "bawang merah 5 bh.",
            "item_original": "bawang merah",
            "item_normalized": "bawang merah",
            "quantity": 5.0,
            "unit": "buah"
          },
          {
            "original_text": "air djeruk 2 sdm.",
            "item_original": "air djeruk",
            "item_normalized": "air jeruk",
            "quantity": 2.0,
            "unit": "sendok makan"
          },
          {
            "original_text": "garam ½ sdt.",
            "item_original": "garam",
            "item_normalized": "garam",
            "quantity": 0.5,
            "unit": "sendok teh"
          },
          {
            "original_text": "lombok merah 3 bdj.",
            "item_original": "lombok merah",
            "item_normalized": "cabai merah",
            "quantity": 3.0,
            "unit": "biji"
          },
          {
            "original_text": "minjak 1 sdm.",
            "item_original": "minjak",
            "item_normalized": "minyak",
            "quantity": 1.0,
            "unit": "sendok makan"
          }
        ]
      }
    ],
    "instructions": [
      "Terong diiris-iris.",
      "Kelapa dibakar, kemudian diparut.",
      "Bumbu dihaluskan, ditumis, parutan kelapa bakar dicampurkan, digoreng sampai kuning.",
      "Air jeruk diseduh dengan air panas sedikit, dituangkan dalam tumisan.",
      "Setelah masak disiramkan ke atas terong mentah."
    ]
  }
]