[
  {
    "recipe_id": "MR_595_587a",
    "title_original": null,
    "title_normalized": null,
    "region": null,
    "page_number": 587,
    "category": "Continuation",
    "ingredient_groups": [
      {
        "group_name": "bumbu",
        "original_header": "Bumbu²:",
        "ingredients": [
          {
            "original_text": "bawang merah 5 bh.",
            "item_original": "bawang merah",
            "item_normalized": "bawang merah",
            "quantity": 5.0,
            "unit": "buah"
          },
          {
            "original_text": "bawang putih 1 siung",
            "item_original": "bawang putih",
            "item_normalized": "bawang putih",
            "quantity": 1.0,
            "unit": "siung"
          },
          {
            "original_text": "lombok merah 4 bh.",
            "item_original": "lombok merah",
            "item_normalized": "cabai merah",
            "quantity": 4.0,
            "unit": "buah"
          },
          {
            "original_text": "salam 2 hl.",
            "item_original": "salam",
            "item_normalized": "daun salam",
            "quantity": 2.0,
            "unit": "helai"
          },
          {
            "original_text": "sereh 1 btg.",
            "item_original": "sereh",
            "item_normalized": "serai",
            "quantity": 1.0,
            "unit": "batang"
          },
          {
            "original_text": "garam 2 sdm.",
            "item_original": "garam",
            "item_normalized": "garam",
            "quantity": 2.0,
            "unit": "sendok makan"
          }
        ]
      }
    ],
    "instructions": [
      "Ikan dibersihkan dan dipotong-potong, diberi garam dan nasi sambil diremas-remas; dimasukkan stoples, dibungkus serbet dan disimpan 3 hari ditempat jang agak panas.",
      "Bumbu diiris halus dan ditjam-pur dengan ikan.",
      "Tjam-puran ini dibung-kusi daun pisang (dua potong tiap bungkus) dan dipanggang."
    ]
  },
  {
    "recipe_id": "MR_595_587b",
    "title_original": "SETUP BUNTJIS",
    "title_normalized": "Setup Buncis",
    "region": "Purwokerto",
    "page_number": 587,
    "category": "Sayuran",
    "ingredient_groups": [
      {
        "group_name": "bahan",
        "original_header": "Bahan²:",
        "ingredients": [
          {
            "original_text": "buntjis 1/2 kg.",
            "item_original": "buntjis",
            "item_normalized": "buncis",
            "quantity": 0.5,
            "unit": "kilogram"
          },
          {
            "original_text": "susu sapi 1/2 gls.",
            "item_original": "susu sapi",
            "item_normalized": "susu sapi",
            "quantity": 0.5,
            "unit": "gelas"
          },
          {
            "original_text": "mentega 1 sdm.",
            "item_original": "mentega",
            "item_normalized": "mentega",
            "quantity": 1.0,
            "unit": "sendok makan"
          },
          {
            "original_text": "tomat 1 bh.",
            "item_original": "tomat",
            "item_normalized": "tomat",
            "quantity": 1.0,
            "unit": "buah"
          }
        ]
      },
      {
        "group_name": "bumbu",
        "original_header": "Bumbu²:",
        "ingredients": [
          {
            "original_text": "lada 1/2 sdt.",
            "item_original": "lada",
            "item_normalized": "lada",
            "quantity": 0.5,
            "unit": "sendok teh"
          },
          {
            "original_text": "pala 1/4 sdt.",
            "item_original": "pala",
            "item_normalized": "pala",
            "quantity": 0.25,
            "unit": "sendok teh"
          },
          {
            "original_text": "garam 1 sdt.",
            "item_original": "garam",
            "item_normalized": "garam",
            "quantity": 1.0,
            "unit": "sendok teh"
          }
        ]
      }
    ],
    "instructions": [
      "Buntjis di-potong² pendek, dibatjem dengan mentega.",
      "Lombok di-potong² tipis, dimasukkan.",
      "Susu dituangkan kedalamnja.",
      "Garam dan lada dimasukkan, dimasak sampai kering."
    ]
  },
  {
    "recipe_id": "MR_595_587c",
    "title_original": "SETUP BUNTJIS BULAT",
    "title_normalized": "Setup Buncis Bulat",
    "region": null,
    "page_number": 587,
    "category": "Sayuran",
    "ingredient_groups": [
      {
        "group_name": "bahan",
        "original_header": "Bahan²:",
        "ingredients": [
          {
            "original_text": "buntjis 1/2 kg.",
            "item_original": "buntjis",
            "item_normalized": "buncis",
            "quantity": 0.5,
            "unit": "kilogram"
          },
          {
            "original_text": "mentega 2 sdm.",
            "item_original": "mentega",
            "item_normalized": "mentega",
            "quantity": 2.0,
            "unit": "sendok makan"
          }
        ]
      },
      {
        "group_name": "bumbu",
        "original_header": "Bumbu²:",
        "ingredients": [
          {
            "original_text": "garam 1/2 sdt.",
            "item_original": "garam",
            "item_normalized": "garam",
            "quantity": 0.5,
            "unit": "sendok teh"
          },
          {
            "original_text": "pala 1 sdt.",
            "item_original": "pala",
            "item_normalized": "pala",
            "quantity": 1.0,
            "unit": "sendok teh"
          }
        ]
      }
    ],
    "instructions": []
  }
]