[
  {
    "recipe_id": "MR_564_1",
    "title_original": "PETJEL PANGGANG IKAN",
    "title_normalized": "Pecel Panggang Ikan",
    "region": "Rembang",
    "page_number": 564,
    "category": "Lauk Pauk",
    "ingredient_groups": [
      {
        "group_name": "utama",
        "original_header": "Bahan²",
        "ingredients": [
          {
            "original_text": "ikan panggang laut ½ kg.",
            "item_original": "ikan panggang laut",
            "item_normalized": "ikan panggang laut",
            "quantity": 0.5,
            "unit": "kilogram"
          },
          {
            "original_text": "kelapa ½ btr.",
            "item_original": "kelapa",
            "item_normalized": "kelapa",
            "quantity": 0.5,
            "unit": "butir"
          }
        ]
      },
      {
        "group_name": "bumbu",
        "original_header": "Bumbu²",
        "ingredients": [
          {
            "original_text": "bawang merah 3 bh.",
            "item_original": "bawang merah",
            "item_normalized": "bawang merah",
            "quantity": 3.0,
            "unit": "buah"
          },
          {
            "original_text": "bawang putih 2 siung",
            "item_original": "bawang putih",
            "item_normalized": "bawang putih",
            "quantity": 2.0,
            "unit": "siung"
          },
          {
            "original_text": "lombok merah 5 bh.",
            "item_original": "lombok merah",
            "item_normalized": "cabai merah",
            "quantity": 5.0,
            "unit": "buah"
          },
          {
            "original_text": "kemiri 3 bdj.",
            "item_original": "kemiri",
            "item_normalized": "kemiri",
            "quantity": 3.0,
            "unit": "biji"
          },
          {
            "original_text": "kentjur ½ rdj.",
            "item_original": "kentjur",
            "item_normalized": "kencur",
            "quantity": 0.5,
            "unit": "ruas jari"
          },
          {
            "original_text": "garam ½ sdm.",
            "item_original": "garam",
            "item_normalized": "garam",
            "quantity": 0.5,
            "unit": "sendok makan"
          }
        ]
      }
    ],
    "instructions": [
      "Kelapa diparut, diambil santan kental 1 gelas.",
      "Semua bumbu dibersihkan, dihaluskan.",
      "Direbus dengan air ± 1 tjangkir sampai mendidih. Ikan dimasukkan, terachir santan.",
      "Dimasak sampai kental."
    ]
  },
  {
    "recipe_id": "MR_564_2",
    "title_original": "PETJEL TERONG",
    "title_normalized": "Pecel Terong",
    "region": "Banyumas",
    "page_number": 564,
    "category": "Lauk Pauk",
    "ingredient_groups": [
      {
        "group_name": "utama",
        "original_header": "Bahan²",
        "ingredients": [
          {
            "original_text": "terong 5 bh.",
            "item_original": "terong",
            "item_normalized": "terong",
            "quantity": 5.0,
            "unit": "buah"
          },
          {
            "original_text": "kelapa ½ btr.",
            "item_original": "kelapa",
            "item_normalized": "kelapa",
            "quantity": 0.5,
            "unit": "butir"
          },
          {
            "original_text": "tempe bosok 1 pt.",
            "item_original": "tempe bosok",
            "item_normalized": "tempe busuk",
            "quantity": 1.0,
            "unit": "potong"
          }
        ]
      },
      {
        "group_name": "bumbu",
        "original_header": "Bumbu²",
        "ingredients": [
          {
            "original_text": "lombok merah 2 bh.",
            "item_original": "lombok merah",
            "item_normalized": "cabai merah",
            "quantity": 2.0,
            "unit": "buah"
          },
          {
            "original_text": "gula 2 sdm.",
            "item_original": "gula",
            "item_normalized": "gula",
            "quantity": 2.0,
            "unit": "sendok makan"
          }
        ]
      }
    ],
    "instructions": []
  }
]